{"base_uuid": "fa83ff0a-5066-4c01-bdf6-909bc3dda074", "unique_uuid": "2bf1e931-e978-4ae5-b56a-366dd934d6df", "number_of_points": 35, "z_score": -1.8321634017832285, "vacuumed_z_score": -1.0675044834973326, "std_vaccumed_z_score": -2.009890201349982, "flipped": false, "group": "clustered", "points": [{"x": 566, "y": 90}, {"x": 103, "y": 462}, {"x": 739, "y": 198}, {"x": 422, "y": 32}, {"x": 328, "y": 152}, {"x": 344, "y": 363}, {"x": 543, "y": 100}, {"x": 399, "y": 76}, {"x": 681, "y": 24}, {"x": 388, "y": 244}, {"x": 605, "y": 244}, {"x": 27, "y": 92}, {"x": 124, "y": 276}, {"x": 467, "y": 65}, {"x": 324, "y": 185}, {"x": 448, "y": 278}, {"x": 425, "y": 486}, {"x": 279, "y": 167}, {"x": 684, "y": 471}, {"x": 154, "y": 139}, {"x": 162, "y": 463}, {"x": 160, "y": 292}, {"x": 561, "y": 234}, {"x": 445, "y": 154}, {"x": 649, "y": 443}, {"x": 688, "y": 85}, {"x": 36, "y": 110}, {"x": 178, "y": 440}, {"x": 150, "y": 73}, {"x": 57, "y": 262}, {"x": 347, "y": 213}, {"x": 420, "y": 457}, {"x": 756, "y": 257}, {"x": 500, "y": 317}, {"x": 400, "y": 379}], "practice_stimulus": false}